aiorexense/__init__.py
aiorexense/api.py
aiorexense/const.py
aiorexense/py.typed
aiorexense/ws_client.py
aiorexense-0.1.4.dist-info/licenses/LICENSE
aiorexense-0.1.4.dist-info/METADATA
aiorexense-0.1.4.dist-info/WHEEL
aiorexense-0.1.4.dist-info/top_level.txt
aiorexense-0.1.4.dist-info/RECORD
