Metadata-Version: 2.4
Name: aiorexense
Version: 0.1.4
Summary: Rexense device client library: HTTP API + WebSocket
Home-page: https://github.com/RexenseIoT/aiorexense.git
Author: Zhejiang Rexense IoT Technology Co., Ltd
Author-email: RexenseIoT <yuxiaoqiang@rexense.com>
License: MIT License
Project-URL: Homepage, https://github.com/RexenseIoT/aiorexense.git
Project-URL: Repository, https://github.com/RexenseIoT/aiorexense.git
Requires-Python: >=3.8
License-File: LICENSE
Requires-Dist: aiohttp>=3.8.0
Dynamic: author
Dynamic: home-page
Dynamic: license-file
Dynamic: requires-python
